ibapi/__init__.py
ibapi/account_summary_tags.py
ibapi/client.py
ibapi/client_utils.py
ibapi/comm.py
ibapi/commission_and_fees_report.py
ibapi/common.py
ibapi/connection.py
ibapi/const.py
ibapi/contract.py
ibapi/decoder.py
ibapi/decoder_utils.py
ibapi/enum_implem.py
ibapi/errors.py
ibapi/execution.py
ibapi/ineligibility_reason.py
ibapi/message.py
ibapi/news.py
ibapi/object_implem.py
ibapi/order.py
ibapi/order_cancel.py
ibapi/order_condition.py
ibapi/order_state.py
ibapi/orderdecoder.py
ibapi/reader.py
ibapi/scanner.py
ibapi/server_versions.py
ibapi/softdollartier.py
ibapi/sync_wrapper.py
ibapi/tag_value.py
ibapi/ticktype.py
ibapi/utils.py
ibapi/wrapper.py
ibapi/protobuf/AccountDataEnd_pb2.py
ibapi/protobuf/AccountDataRequest_pb2.py
ibapi/protobuf/AccountSummaryEnd_pb2.py
ibapi/protobuf/AccountSummaryRequest_pb2.py
ibapi/protobuf/AccountSummary_pb2.py
ibapi/protobuf/AccountUpdateMultiEnd_pb2.py
ibapi/protobuf/AccountUpdateMulti_pb2.py
ibapi/protobuf/AccountUpdateTime_pb2.py
ibapi/protobuf/AccountUpdatesMultiRequest_pb2.py
ibapi/protobuf/AccountValue_pb2.py
ibapi/protobuf/AllOpenOrdersRequest_pb2.py
ibapi/protobuf/AttachedOrders_pb2.py
ibapi/protobuf/AutoOpenOrdersRequest_pb2.py
ibapi/protobuf/CalculateImpliedVolatilityRequest_pb2.py
ibapi/protobuf/CalculateOptionPriceRequest_pb2.py
ibapi/protobuf/CancelAccountSummary_pb2.py
ibapi/protobuf/CancelAccountUpdatesMulti_pb2.py
ibapi/protobuf/CancelCalculateImpliedVolatility_pb2.py
ibapi/protobuf/CancelCalculateOptionPrice_pb2.py
ibapi/protobuf/CancelContractData_pb2.py
ibapi/protobuf/CancelFundamentalsData_pb2.py
ibapi/protobuf/CancelHeadTimestamp_pb2.py
ibapi/protobuf/CancelHistogramData_pb2.py
ibapi/protobuf/CancelHistoricalData_pb2.py
ibapi/protobuf/CancelHistoricalTicks_pb2.py
ibapi/protobuf/CancelMarketData_pb2.py
ibapi/protobuf/CancelMarketDepth_pb2.py
ibapi/protobuf/CancelNewsBulletins_pb2.py
ibapi/protobuf/CancelOrderRequest_pb2.py
ibapi/protobuf/CancelPnLSingle_pb2.py
ibapi/protobuf/CancelPnL_pb2.py
ibapi_latest-10.42.1.dist-info/licenses/LICENSE
ibapi_latest-10.42.1.dist-info/METADATA
ibapi_latest-10.42.1.dist-info/WHEEL
ibapi_latest-10.42.1.dist-info/top_level.txt
ibapi_latest-10.42.1.dist-info/RECORD
