Metadata-Version: 2.4
Name: ibapi-latest
Version: 10.42.1
Summary: Interactive Brokers Python API
Author-email: Interactive Brokers LLC <api@interactivebrokers.com>
Maintainer: IB API Automated Publisher
Project-URL: Homepage, https://interactivebrokers.github.io/tws-api
Project-URL: Documentation, https://ibkrcampus.com/ibkr-api-page/
Project-URL: Repository, https://github.com/yourusername/ibapi
Project-URL: Bug Tracker, https://github.com/yourusername/ibapi/issues
Keywords: interactive brokers,ibapi,tws,trading,api
Classifier: Development Status :: 5 - Production/Stable
Classifier: Intended Audience :: Developers
Classifier: Intended Audience :: Financial and Insurance Industry
Classifier: Topic :: Office/Business :: Financial :: Investment
Classifier: Programming Language :: Python :: 3
Classifier: Programming Language :: Python :: 3.7
Classifier: Programming Language :: Python :: 3.8
Classifier: Programming Language :: Python :: 3.9
Classifier: Programming Language :: Python :: 3.10
Classifier: Programming Language :: Python :: 3.11
Classifier: Programming Language :: Python :: 3.12
Requires-Python: >=3.1
License-File: LICENSE
Requires-Dist: protobuf==5.29.3
Dynamic: license-file
